{
    "objectID": 7570,
    "itemInfo": {
        "name": "Shoulder Parrot Red",
        "displayName": "Red Shoulder Parrot",
        "type": "Loot",
        "description": null,
        "internalNotes": "2 AP 2 IP"
    },
    "components": {
        "2": 7133,
        "9": 0,
        "11": 3213
    },
    "skillIDs": [
        361,
        370
    ],
    "objectSkills": {
        "361": {
            "castOnType": 1,
            "AICombatWeight": 0,
            "behaviorID": 4243,
            "imaginationcost": 0,
            "cooldowngroup": 16,
            "cooldown": 0.0,
            "inNpcEditor": 0,
            "skillIcon": 3120,
            "imBonusUI": null,
            "lifeBonusUI": null,
            "armorBonusUI": 2
        },
        "370": {
            "castOnType": 1,
            "AICombatWeight": 0,
            "behaviorID": 4252,
            "imaginationcost": 0,
            "cooldowngroup": 16,
            "cooldown": 0.0,
            "inNpcEditor": 0,
            "skillIcon": 1032,
            "imBonusUI": 2,
            "lifeBonusUI": null,
            "armorBonusUI": null
        }
    },
    "behaviorIDs": [
        4243,
        4252
    ],
    "stats": {
        "armorBonusUI": 2,
        "imBonusUI": 2
    },
    "itemComponent": {
        "equipLocation": [
            "clavicle"
        ],
        "sellPrice": 815,
        "buyPrice": 8150,
        "isKitPiece": 0,
        "rarity": 4,
        "itemComponent": null,
        "inLootTable": 1,
        "inVendor": 1,
        "stackSize": 1,
        "color": -1,
        "preconditions": [
            214
        ],
        "isTwoHanded": 0,
        "altCurrencyType": null,
        "altCurrencyCost": null,
        "subItems": null,
        "commendationCurrencyType": null,
        "commendationCurrencyCost": null,
        "equipLocationNames": [
            "Neck/Back"
        ],
        "isWeapon": false,
        "levelRequirement": "15"
    },
    "iconURL": "https://xiphoseer.github.io/lu-res/textures/ui/inventory/models/m2546_21.png",
    "buyAndDrop": {
        "LootTableIndexes": [
            104,
            362
        ],
        "LootMatrixIndexesArray": [
            216,
            217,
            218,
            445,
            567,
            568,
            569,
            570,
            571,
            572,
            573,
            620,
            665,
            870,
            871,
            872
        ],
        "LootMatrixIndexes": {
            "216": {
                "LootMatrixIndex": 216,
                "RarityTableIndex": 4,
                "percent": 0.25,
                "minToDrop": 1,
                "maxToDrop": 1,
                "DestructibleComponent": {
                    "comp_val": 1892,
                    "enemyID": null,
                    "enemyNames": null
                },
                "inNpcEditor": 0
            },
            "217": {
                "LootMatrixIndex": 217,
                "RarityTableIndex": 4,
                "percent": 0.5,
                "minToDrop": 1,
                "maxToDrop": 1,
                "DestructibleComponent": {
                    "comp_val": 1893,
                    "enemyID": null,
                    "enemyNames": null
                },
                "inNpcEditor": 0
            },
            "218": {
                "LootMatrixIndex": 218,
                "RarityTableIndex": 4,
                "percent": 2.0,
                "minToDrop": 1,
                "maxToDrop": 1,
                "DestructibleComponent": {
                    "comp_val": 985,
                    "enemyID": null,
                    "enemyNames": null
                },
                "inNpcEditor": 0
            },
            "445": {
                "LootMatrixIndex": 445,
                "RarityTableIndex": 26,
                "percent": 100.0,
                "minToDrop": 1,
                "maxToDrop": 1,
                "DestructibleComponent": {},
                "inNpcEditor": 0
            },
            "567": {
                "LootMatrixIndex": 567,
                "RarityTableIndex": 29,
                "percent": 1.0,
                "minToDrop": 1,
                "maxToDrop": 1,
                "DestructibleComponent": {},
                "inNpcEditor": 0
            },
            "568": {
                "LootMatrixIndex": 568,
                "RarityTableIndex": 29,
                "percent": 5.0,
                "minToDrop": 1,
                "maxToDrop": 1,
                "DestructibleComponent": {},
                "inNpcEditor": 0
            },
            "569": {
                "LootMatrixIndex": 569,
                "RarityTableIndex": 29,
                "percent": 10.0,
                "minToDrop": 1,
                "maxToDrop": 1,
                "DestructibleComponent": {},
                "inNpcEditor": 0
            },
            "570": {
                "LootMatrixIndex": 570,
                "RarityTableIndex": 29,
                "percent": 20.0,
                "minToDrop": 1,
                "maxToDrop": 1,
                "DestructibleComponent": {},
                "inNpcEditor": 0
            },
            "571": {
                "LootMatrixIndex": 571,
                "RarityTableIndex": 29,
                "percent": 40.0,
                "minToDrop": 1,
                "maxToDrop": 1,
                "DestructibleComponent": {},
                "inNpcEditor": 0
            },
            "572": {
                "LootMatrixIndex": 572,
                "RarityTableIndex": 29,
                "percent": 77.0,
                "minToDrop": 1,
                "maxToDrop": 1,
                "DestructibleComponent": {},
                "inNpcEditor": 0
            },
            "573": {
                "LootMatrixIndex": 573,
                "RarityTableIndex": 29,
                "percent": 100.0,
                "minToDrop": 1,
                "maxToDrop": 1,
                "DestructibleComponent": {},
                "inNpcEditor": 0
            },
            "620": {
                "LootMatrixIndex": 620,
                "RarityTableIndex": 4,
                "percent": 100.0,
                "minToDrop": 1,
                "maxToDrop": 1,
                "DestructibleComponent": {
                    "comp_val": 1755,
                    "enemyID": 12591,
                    "enemyNames": {
                        "name": "NSI - Stromling Ape Boss",
                        "displayName": "Kinga Hurl - Stromling Ape"
                    }
                },
                "inNpcEditor": 0
            },
            "665": {
                "LootMatrixIndex": 665,
                "RarityTableIndex": 4,
                "percent": 50.0,
                "minToDrop": 2,
                "maxToDrop": 3,
                "DestructibleComponent": {},
                "inNpcEditor": 0
            },
            "870": {
                "LootMatrixIndex": 870,
                "RarityTableIndex": 4,
                "percent": 4.0,
                "minToDrop": 1,
                "maxToDrop": 1,
                "DestructibleComponent": {
                    "comp_val": 2144,
                    "enemyID": null,
                    "enemyNames": null
                },
                "inNpcEditor": 1
            },
            "871": {
                "LootMatrixIndex": 871,
                "RarityTableIndex": 4,
                "percent": 6.0,
                "minToDrop": 1,
                "maxToDrop": 1,
                "DestructibleComponent": {
                    "comp_val": 2145,
                    "enemyID": null,
                    "enemyNames": null
                },
                "inNpcEditor": 1
            },
            "872": {
                "LootMatrixIndex": 872,
                "RarityTableIndex": 4,
                "percent": 10.0,
                "minToDrop": 1,
                "maxToDrop": 1,
                "DestructibleComponent": {
                    "comp_val": 2146,
                    "enemyID": null,
                    "enemyNames": null
                },
                "inNpcEditor": 1
            }
        },
        "VendorComponents": [],
        "VendorIDs": [],
        "Vendors": [],
        "DestructibleComponents": [
            66,
            92,
            2144,
            2145,
            2146,
            104,
            106,
            157,
            167,
            206,
            295,
            296,
            297,
            298,
            300,
            301,
            302,
            303,
            304,
            351,
            504,
            584,
            585,
            631,
            633,
            638,
            640,
            985,
            1755,
            1892,
            1893
        ],
        "EnemyIDs": [
            6550,
            6789,
            6806,
            12591
        ],
        "Enemies": [
            {
                "id": 6550,
                "name": "GF - Stromling Pirate",
                "displayName": "Stromling Pirate"
            },
            {
                "id": 6789,
                "name": "GF - Stromling Admiral",
                "displayName": "Stromling Admiral"
            },
            {
                "id": 6806,
                "name": "GF - Stromling Ape",
                "displayName": "Stromling Ape"
            },
            {
                "id": 12591,
                "name": "NSI - Stromling Ape Boss",
                "displayName": "Kinga Hurl - Stromling Ape"
            }
        ]
    }
}