{
    "overview": {
        "hasChargeUp": false,
        "spawnsObject": false,
        "spawnsQuickbuild": false,
        "meleeAttack": false,
        "projectileAttack": false,
        "damageComboArray": [],
        "chargeUpArmorRestore": [],
        "chargeUpImaginationRestore": [],
        "projectileLOTs": [],
        "projectileInfo": {},
        "projectileDamageComboArray": [],
        "chargeUpCombo": 0
    },
    "projectileBehaviorIDs": [],
    "projectileChargeUpBehaviorIDs": [],
    "behavior 1": {
        "initial_value": 38529
    },
    "behavior 2": {
        "initial_value": 38530
    },
    "38528": {
        "name": {
            "templateID": 3,
            "behaviorTemplateName": "And",
            "effectID": 0
        },
        "hasKids": true,
        "info": {
            "behavior 1": 38529,
            "behavior 2": 38530
        },
        "kids": {
            "38529": {
                "name": {
                    "templateID": 8,
                    "behaviorTemplateName": "PlayEffect",
                    "effectID": 9111
                },
                "hasKids": false,
                "info": {},
                "kids": {}
            },
            "38530": {
                "name": {
                    "templateID": 55,
                    "behaviorTemplateName": "Taunt",
                    "effectID": 0
                },
                "hasKids": true,
                "info": {
                    "threat to add": 500
                },
                "kids": {}
            }
        }
    }
}