{
    "overview": {
        "hasChargeUp": false,
        "spawnsObject": false,
        "spawnsQuickbuild": false,
        "meleeAttack": false,
        "projectileAttack": false,
        "damageComboArray": [],
        "chargeUpArmorRestore": [],
        "chargeUpImaginationRestore": [],
        "projectileLOTs": [],
        "projectileInfo": {},
        "projectileDamageComboArray": [],
        "chargeUpCombo": 0
    },
    "projectileBehaviorIDs": [],
    "projectileChargeUpBehaviorIDs": [],
    "duration": {
        "initial_value": 0
    },
    "forward": {
        "initial_value": 0
    },
    "left": {
        "initial_value": 0
    },
    "move_target": {
        "initial_value": 0
    },
    "relative": {
        "initial_value": 1
    },
    "yaw": {
        "initial_value": 0
    },
    "yaw_abs": {
        "initial_value": 0
    },
    "17272": {
        "name": {
            "templateID": 40,
            "behaviorTemplateName": "ForceMovement",
            "effectID": 0
        },
        "hasKids": true,
        "info": {
            "duration": 0,
            "forward": 0,
            "left": 0,
            "move_target": 0,
            "relative": 1,
            "yaw": 0,
            "yaw_abs": 0
        },
        "kids": {}
    }
}