{
    "overview": {
        "hasChargeUp": false,
        "spawnsObject": false,
        "spawnsQuickbuild": false,
        "meleeAttack": true,
        "projectileAttack": false,
        "damageComboArray": [
            1,
            4
        ],
        "chargeUpArmorRestore": [],
        "chargeUpImaginationRestore": [],
        "projectileLOTs": [],
        "projectileInfo": {},
        "projectileDamageComboArray": [],
        "chargeUpCombo": 0
    },
    "projectileBehaviorIDs": [],
    "projectileChargeUpBehaviorIDs": [],
    "action": {
        "initial_value": 38120
    },
    "delay": {
        "initial_value": 0
    },
    "ignore_interrupts": {
        "initial_value": 1
    },
    "num_intervals": {
        "initial_value": 1
    },
    "38119": {
        "name": {
            "templateID": 18,
            "behaviorTemplateName": "AttackDelay",
            "effectID": 9025
        },
        "hasKids": true,
        "info": {
            "action": 38120,
            "delay": 0,
            "ignore_interrupts": 1,
            "num_intervals": 1
        },
        "kids": {
            "38120": {
                "name": {
                    "templateID": 3,
                    "behaviorTemplateName": "And",
                    "effectID": 0
                },
                "hasKids": true,
                "info": {
                    "behavior 1": 38121,
                    "behavior 2": 38122
                },
                "kids": {
                    "38121": {
                        "name": {
                            "templateID": 8,
                            "behaviorTemplateName": "PlayEffect",
                            "effectID": 9026
                        },
                        "hasKids": false,
                        "info": {},
                        "kids": {}
                    },
                    "38122": {
                        "name": {
                            "templateID": 56,
                            "behaviorTemplateName": "AirMovement",
                            "effectID": 0
                        },
                        "hasKids": true,
                        "info": {
                            "goto_target": 0,
                            "gravity_scale": 1,
                            "ground_action": 38123,
                            "hit_action": 38123,
                            "hit_action_enemy": 38123,
                            "timeout_action": 38123,
                            "timeout_ms": 2000,
                            "x_velocity": 0,
                            "y_velocity": -25,
                            "z_velocity": 0
                        },
                        "kids": {
                            "38123": {
                                "name": {
                                    "templateID": 3,
                                    "behaviorTemplateName": "And",
                                    "effectID": 0
                                },
                                "hasKids": true,
                                "info": {
                                    "behavior 1": 38124,
                                    "behavior 2": 38125,
                                    "behavior 3": 38127,
                                    "behavior 4": 38136
                                },
                                "kids": {
                                    "38124": {
                                        "name": {
                                            "templateID": 8,
                                            "behaviorTemplateName": "PlayEffect",
                                            "effectID": 9027
                                        },
                                        "hasKids": false,
                                        "info": {},
                                        "kids": {}
                                    },
                                    "38125": {
                                        "name": {
                                            "templateID": 16,
                                            "behaviorTemplateName": "Duration",
                                            "effectID": 0
                                        },
                                        "hasKids": true,
                                        "info": {
                                            "action": 38126,
                                            "duration": 0
                                        },
                                        "kids": {
                                            "38126": {
                                                "name": {
                                                    "templateID": 15,
                                                    "behaviorTemplateName": "Stun",
                                                    "effectID": 0
                                                },
                                                "hasKids": true,
                                                "info": {
                                                    "cant_attack": 1,
                                                    "cant_equip": 1,
                                                    "cant_interact": 1,
                                                    "cant_move": 1,
                                                    "cant_turn": 1,
                                                    "stun_caster": 1
                                                },
                                                "kids": {}
                                            }
                                        }
                                    },
                                    "38127": {
                                        "name": {
                                            "templateID": 7,
                                            "behaviorTemplateName": "AoE",
                                            "effectID": 0
                                        },
                                        "hasKids": true,
                                        "info": {
                                            "action": 38128,
                                            "include_faction": 14,
                                            "max targets": 20,
                                            "radius": 5,
                                            "target_enemy": 1,
                                            "target_friend": 0,
                                            "target_self": 0,
                                            "target_team": 0,
                                            "use_target_as_caster": 0,
                                            "use_target_position": 0
                                        },
                                        "kids": {
                                            "38128": {
                                                "name": {
                                                    "templateID": 29,
                                                    "behaviorTemplateName": "Switch",
                                                    "effectID": 0
                                                },
                                                "hasKids": true,
                                                "info": {
                                                    "action_false": 38129,
                                                    "action_true": 38135,
                                                    "distance": -1,
                                                    "imagination": 0,
                                                    "isEnemyFaction": 0,
                                                    "target_has_buff": 2
                                                },
                                                "kids": {
                                                    "38129": {
                                                        "name": {
                                                            "templateID": 1,
                                                            "behaviorTemplateName": "BasicAttack",
                                                            "effectID": 9028
                                                        },
                                                        "hasKids": true,
                                                        "info": {
                                                            "dir_angle_xz": 0,
                                                            "dir_angle_y": 30,
                                                            "dir_force": 15,
                                                            "dont_apply_immune": 0,
                                                            "max damage": 1,
                                                            "min damage": 1,
                                                            "on_fail_armor": 38130,
                                                            "on_success": 38130,
                                                            "use_caster_velocity": 0,
                                                            "velocity_multiplier": 1
                                                        },
                                                        "kids": {
                                                            "38130": {
                                                                "name": {
                                                                    "templateID": 3,
                                                                    "behaviorTemplateName": "And",
                                                                    "effectID": 0
                                                                },
                                                                "hasKids": true,
                                                                "info": {
                                                                    "behavior 1": 38131,
                                                                    "behavior 2": 38132,
                                                                    "behavior 3": 38134
                                                                },
                                                                "kids": {
                                                                    "38131": {
                                                                        "name": {
                                                                            "templateID": 41,
                                                                            "behaviorTemplateName": "Interrupt",
                                                                            "effectID": 0
                                                                        },
                                                                        "hasKids": true,
                                                                        "info": {
                                                                            "interrupt_attack": 1,
                                                                            "interrupt_block": 0,
                                                                            "interrupt_charge": 1,
                                                                            "target": 1
                                                                        },
                                                                        "kids": {}
                                                                    },
                                                                    "38132": {
                                                                        "name": {
                                                                            "templateID": 16,
                                                                            "behaviorTemplateName": "Duration",
                                                                            "effectID": 0
                                                                        },
                                                                        "hasKids": true,
                                                                        "info": {
                                                                            "action": 38133,
                                                                            "duration": 0
                                                                        },
                                                                        "kids": {
                                                                            "38133": {
                                                                                "name": {
                                                                                    "templateID": 15,
                                                                                    "behaviorTemplateName": "Stun",
                                                                                    "effectID": 0
                                                                                },
                                                                                "hasKids": true,
                                                                                "info": {
                                                                                    "cant_attack": 1,
                                                                                    "cant_equip": 1,
                                                                                    "cant_interact": 1,
                                                                                    "cant_move": 1,
                                                                                    "cant_turn": 1,
                                                                                    "stun_caster": 0
                                                                                },
                                                                                "kids": {}
                                                                            }
                                                                        }
                                                                    },
                                                                    "38134": {
                                                                        "name": {
                                                                            "templateID": 17,
                                                                            "behaviorTemplateName": "Knockback",
                                                                            "effectID": 0
                                                                        },
                                                                        "hasKids": true,
                                                                        "info": {
                                                                            "angle": 45,
                                                                            "caster": 0,
                                                                            "ignore_self": 0,
                                                                            "relative": 0,
                                                                            "strength": 15
                                                                        },
                                                                        "kids": {}
                                                                    }
                                                                }
                                                            }
                                                        }
                                                    },
                                                    "38135": {
                                                        "name": {
                                                            "templateID": 1,
                                                            "behaviorTemplateName": "BasicAttack",
                                                            "effectID": 9029
                                                        },
                                                        "hasKids": true,
                                                        "info": {
                                                            "dir_angle_xz": 0,
                                                            "dir_angle_y": 30,
                                                            "dir_force": 15,
                                                            "dont_apply_immune": 0,
                                                            "max damage": 4,
                                                            "min damage": 4,
                                                            "on_fail_armor": 38130,
                                                            "on_success": 38130,
                                                            "use_caster_velocity": 0,
                                                            "velocity_multiplier": 1
                                                        },
                                                        "kids": {}
                                                    }
                                                }
                                            }
                                        }
                                    },
                                    "38136": {
                                        "name": {
                                            "templateID": 46,
                                            "behaviorTemplateName": "End",
                                            "effectID": 0
                                        },
                                        "hasKids": true,
                                        "info": {
                                            "start_action": 38116
                                        },
                                        "kids": {
                                            "38116": {
                                                "name": {
                                                    "templateID": 45,
                                                    "behaviorTemplateName": "Start",
                                                    "effectID": 0
                                                },
                                                "hasKids": true,
                                                "info": {
                                                    "action": 38117
                                                },
                                                "kids": {
                                                    "38117": {
                                                        "name": {
                                                            "templateID": 15,
                                                            "behaviorTemplateName": "Stun",
                                                            "effectID": 0
                                                        },
                                                        "hasKids": true,
                                                        "info": {
                                                            "cant_attack": 1,
                                                            "cant_equip": 1,
                                                            "cant_interact": 1,
                                                            "cant_move": 1,
                                                            "cant_turn": 1,
                                                            "stun_caster": 1
                                                        },
                                                        "kids": {}
                                                    }
                                                }
                                            }
                                        }
                                    }
                                }
                            }
                        }
                    }
                }
            }
        }
    }
}