{
    "overview": {
        "hasChargeUp": false,
        "spawnsObject": false,
        "spawnsQuickbuild": false,
        "meleeAttack": false,
        "projectileAttack": false,
        "damageComboArray": [],
        "chargeUpArmorRestore": [],
        "chargeUpImaginationRestore": [],
        "projectileLOTs": [],
        "projectileInfo": {},
        "projectileDamageComboArray": [],
        "chargeUpCombo": 0
    },
    "projectileBehaviorIDs": [],
    "projectileChargeUpBehaviorIDs": [],
    "behavior 1": {
        "initial_value": 30312
    },
    "behavior 2": {
        "initial_value": 30313
    },
    "behavior 3": {
        "initial_value": 30314
    },
    "30311": {
        "name": {
            "templateID": 3,
            "behaviorTemplateName": "And",
            "effectID": 0
        },
        "hasKids": true,
        "info": {
            "behavior 1": 30312,
            "behavior 2": 30313,
            "behavior 3": 30314
        },
        "kids": {
            "30312": {
                "name": {
                    "templateID": 8,
                    "behaviorTemplateName": "PlayEffect",
                    "effectID": 6641
                },
                "hasKids": false,
                "info": {},
                "kids": {}
            },
            "30313": {
                "name": {
                    "templateID": 8,
                    "behaviorTemplateName": "PlayEffect",
                    "effectID": 6642
                },
                "hasKids": false,
                "info": {},
                "kids": {}
            },
            "30314": {
                "name": {
                    "templateID": 8,
                    "behaviorTemplateName": "PlayEffect",
                    "effectID": 6643
                },
                "hasKids": false,
                "info": {},
                "kids": {}
            }
        }
    }
}