{
    "itemsList": [
        16276
    ],
    "items": {
        "16276": {
            "itemComponent": 7567,
            "rarity": 3,
            "name": "Ice Spinjitzu Hood Hood of Frost",
            "displayName": "Hood of Frost"
        }
    },
    "itemComponentValues": [
        7567
    ],
    "rarityCount": {
        "1": 0,
        "2": 0,
        "3": 1,
        "4": 0,
        "5": 0
    },
    "nameInfo": {
        "LootTableIndex": "861",
        "Type": "Loot",
        "Name": "Ice Spinjitzu Hood Hood of Frost",
        "AlternateName": "Hood of Frost"
    }
}