{
    "overview": {
        "hasChargeUp": false,
        "spawnsObject": false,
        "spawnsQuickbuild": false,
        "meleeAttack": true,
        "projectileAttack": false,
        "damageComboArray": [],
        "chargeUpArmorRestore": [],
        "chargeUpImaginationRestore": [],
        "projectileLOTs": [],
        "projectileInfo": {},
        "projectileDamageComboArray": [],
        "chargeUpCombo": 0
    },
    "projectileBehaviorIDs": [],
    "projectileChargeUpBehaviorIDs": [],
    "behavior 1": {
        "initial_value": 8460
    },
    "behavior 2": {
        "initial_value": 8462
    },
    "behavior 3": {
        "initial_value": 8463
    },
    "behavior 4": {
        "initial_value": 8464
    },
    "8459": {
        "name": {
            "templateID": 3,
            "behaviorTemplateName": "And",
            "effectID": 0
        },
        "hasKids": true,
        "info": {
            "behavior 1": 8460,
            "behavior 2": 8462,
            "behavior 3": 8463,
            "behavior 4": 8464
        },
        "kids": {
            "8460": {
                "name": {
                    "templateID": 16,
                    "behaviorTemplateName": "Duration",
                    "effectID": 0
                },
                "hasKids": true,
                "info": {
                    "action": 8461,
                    "duration": 0
                },
                "kids": {
                    "8461": {
                        "name": {
                            "templateID": 15,
                            "behaviorTemplateName": "Stun",
                            "effectID": 0
                        },
                        "hasKids": true,
                        "info": {
                            "cant_attack": 0,
                            "cant_equip": 1,
                            "cant_interact": 1,
                            "cant_move": 1,
                            "cant_turn": 1,
                            "stun_caster": 1
                        },
                        "kids": {}
                    }
                }
            },
            "8462": {
                "name": {
                    "templateID": 42,
                    "behaviorTemplateName": "AlterCooldown",
                    "effectID": 0
                },
                "hasKids": true,
                "info": {
                    "add": 0,
                    "amount": 0
                },
                "kids": {}
            },
            "8463": {
                "name": {
                    "templateID": 47,
                    "behaviorTemplateName": "AlterChainDelay",
                    "effectID": 0
                },
                "hasKids": true,
                "info": {
                    "chain_action": 8440,
                    "new_delay": 1
                },
                "kids": {
                    "8440": {
                        "name": {
                            "templateID": 38,
                            "behaviorTemplateName": "Chain",
                            "effectID": 0
                        },
                        "hasKids": true,
                        "info": {
                            "behavior 1": 8441,
                            "behavior 2": 8459,
                            "behavior 3": 8476,
                            "chain_delay": 1
                        },
                        "kids": {
                            "8441": {
                                "name": {
                                    "templateID": 3,
                                    "behaviorTemplateName": "And",
                                    "effectID": 0
                                },
                                "hasKids": true,
                                "info": {
                                    "behavior 1": 8442,
                                    "behavior 2": 8444,
                                    "behavior 3": 8445,
                                    "behavior 4": 8446
                                },
                                "kids": {
                                    "8442": {
                                        "name": {
                                            "templateID": 16,
                                            "behaviorTemplateName": "Duration",
                                            "effectID": 0
                                        },
                                        "hasKids": true,
                                        "info": {
                                            "action": 8443,
                                            "duration": 0
                                        },
                                        "kids": {
                                            "8443": {
                                                "name": {
                                                    "templateID": 15,
                                                    "behaviorTemplateName": "Stun",
                                                    "effectID": 0
                                                },
                                                "hasKids": true,
                                                "info": {
                                                    "cant_attack": 0,
                                                    "cant_equip": 1,
                                                    "cant_interact": 1,
                                                    "cant_move": 1,
                                                    "cant_turn": 1,
                                                    "stun_caster": 1
                                                },
                                                "kids": {}
                                            }
                                        }
                                    },
                                    "8444": {
                                        "name": {
                                            "templateID": 42,
                                            "behaviorTemplateName": "AlterCooldown",
                                            "effectID": 0
                                        },
                                        "hasKids": true,
                                        "info": {
                                            "add": 0,
                                            "amount": 0
                                        },
                                        "kids": {}
                                    },
                                    "8445": {
                                        "name": {
                                            "templateID": 47,
                                            "behaviorTemplateName": "AlterChainDelay",
                                            "effectID": 0
                                        },
                                        "hasKids": true,
                                        "info": {
                                            "chain_action": 8440,
                                            "new_delay": 1
                                        },
                                        "kids": {}
                                    },
                                    "8446": {
                                        "name": {
                                            "templateID": 2,
                                            "behaviorTemplateName": "TacArc",
                                            "effectID": 0
                                        },
                                        "hasKids": true,
                                        "info": {
                                            "action": 8447,
                                            "angle": 90,
                                            "check_env": 0,
                                            "clear_provided_target": 0,
                                            "height": 2,
                                            "lower_bound": 0,
                                            "max range": 10,
                                            "max targets": 1,
                                            "method": 1,
                                            "min range": 0,
                                            "miss action": 8457,
                                            "target_enemy": 1,
                                            "target_friend": 0,
                                            "target_self": 0,
                                            "upper_bound": 5,
                                            "use_attack_priority": 1,
                                            "use_picked_target": 1
                                        },
                                        "kids": {
                                            "8447": {
                                                "name": {
                                                    "templateID": 3,
                                                    "behaviorTemplateName": "And",
                                                    "effectID": 0
                                                },
                                                "hasKids": true,
                                                "info": {
                                                    "behavior 1": 8448,
                                                    "behavior 2": 8455,
                                                    "behavior 3": 8456
                                                },
                                                "kids": {
                                                    "8448": {
                                                        "name": {
                                                            "templateID": 18,
                                                            "behaviorTemplateName": "AttackDelay",
                                                            "effectID": 1938
                                                        },
                                                        "hasKids": true,
                                                        "info": {
                                                            "action": 8449,
                                                            "delay": 0
                                                        },
                                                        "kids": {
                                                            "8449": {
                                                                "name": {
                                                                    "templateID": 2,
                                                                    "behaviorTemplateName": "TacArc",
                                                                    "effectID": 1939
                                                                },
                                                                "hasKids": true,
                                                                "info": {
                                                                    "action": 8450,
                                                                    "angle": 90,
                                                                    "angle_weight": 0,
                                                                    "blocked action": 8358,
                                                                    "check_env": 1,
                                                                    "clear_provided_target": 0,
                                                                    "distance_weight": 0,
                                                                    "height": 2,
                                                                    "lower_bound": 0,
                                                                    "max range": 9,
                                                                    "max targets": 1,
                                                                    "method": 1,
                                                                    "min range": 0,
                                                                    "target_enemy": 1,
                                                                    "target_friend": 0,
                                                                    "target_self": 0,
                                                                    "upper_bound": 5,
                                                                    "use_attack_priority": 1,
                                                                    "use_picked_target": 0
                                                                },
                                                                "kids": {
                                                                    "8450": {
                                                                        "name": {
                                                                            "templateID": 1,
                                                                            "behaviorTemplateName": "BasicAttack",
                                                                            "effectID": 1940
                                                                        },
                                                                        "hasKids": true,
                                                                        "info": {
                                                                            "dir_angle_xz": -25,
                                                                            "dir_angle_y": 0,
                                                                            "dir_force": 12,
                                                                            "max damage": 2,
                                                                            "min damage": 2,
                                                                            "on_success": 8451
                                                                        },
                                                                        "kids": {
                                                                            "8451": {
                                                                                "name": {
                                                                                    "templateID": 3,
                                                                                    "behaviorTemplateName": "And",
                                                                                    "effectID": 0
                                                                                },
                                                                                "hasKids": true,
                                                                                "info": {
                                                                                    "behavior 1": 8452,
                                                                                    "behavior 2": 8454,
                                                                                    "behavior 3": 8357
                                                                                },
                                                                                "kids": {
                                                                                    "8452": {
                                                                                        "name": {
                                                                                            "templateID": 16,
                                                                                            "behaviorTemplateName": "Duration",
                                                                                            "effectID": 0
                                                                                        },
                                                                                        "hasKids": true,
                                                                                        "info": {
                                                                                            "action": 8453,
                                                                                            "duration": 0
                                                                                        },
                                                                                        "kids": {
                                                                                            "8453": {
                                                                                                "name": {
                                                                                                    "templateID": 15,
                                                                                                    "behaviorTemplateName": "Stun",
                                                                                                    "effectID": 0
                                                                                                },
                                                                                                "hasKids": true,
                                                                                                "info": {
                                                                                                    "cant_attack": 1,
                                                                                                    "cant_equip": 0,
                                                                                                    "cant_interact": 0,
                                                                                                    "cant_move": 1,
                                                                                                    "cant_turn": 1
                                                                                                },
                                                                                                "kids": {}
                                                                                            }
                                                                                        }
                                                                                    },
                                                                                    "8454": {
                                                                                        "name": {
                                                                                            "templateID": 17,
                                                                                            "behaviorTemplateName": "Knockback",
                                                                                            "effectID": 0
                                                                                        },
                                                                                        "hasKids": true,
                                                                                        "info": {
                                                                                            "angle": 10,
                                                                                            "strength": 2
                                                                                        },
                                                                                        "kids": {}
                                                                                    },
                                                                                    "8357": {
                                                                                        "name": {
                                                                                            "templateID": 41,
                                                                                            "behaviorTemplateName": "Interrupt",
                                                                                            "effectID": 0
                                                                                        },
                                                                                        "hasKids": true,
                                                                                        "info": {
                                                                                            "interrupt_attack": 1,
                                                                                            "interrupt_charge": 1,
                                                                                            "target": 1
                                                                                        },
                                                                                        "kids": {}
                                                                                    }
                                                                                }
                                                                            }
                                                                        }
                                                                    },
                                                                    "8358": {
                                                                        "name": {
                                                                            "templateID": 17,
                                                                            "behaviorTemplateName": "Knockback",
                                                                            "effectID": 0
                                                                        },
                                                                        "hasKids": true,
                                                                        "info": {
                                                                            "angle": 0,
                                                                            "caster": 1,
                                                                            "relative": 1,
                                                                            "strength": 2
                                                                        },
                                                                        "kids": {}
                                                                    }
                                                                }
                                                            }
                                                        }
                                                    },
                                                    "8455": {
                                                        "name": {
                                                            "templateID": 39,
                                                            "behaviorTemplateName": "ChangeOrientation",
                                                            "effectID": 0
                                                        },
                                                        "hasKids": true,
                                                        "info": {
                                                            "duration": 0,
                                                            "to_target": 1
                                                        },
                                                        "kids": {}
                                                    },
                                                    "8456": {
                                                        "name": {
                                                            "templateID": 40,
                                                            "behaviorTemplateName": "ForceMovement",
                                                            "effectID": 0
                                                        },
                                                        "hasKids": true,
                                                        "info": {
                                                            "duration": 0,
                                                            "forward": 0,
                                                            "left": 0,
                                                            "move_target": 0,
                                                            "relative": 1,
                                                            "yaw": 0,
                                                            "yaw_abs": 0
                                                        },
                                                        "kids": {}
                                                    }
                                                }
                                            },
                                            "8457": {
                                                "name": {
                                                    "templateID": 2,
                                                    "behaviorTemplateName": "TacArc",
                                                    "effectID": 0
                                                },
                                                "hasKids": true,
                                                "info": {
                                                    "action": 8447,
                                                    "angle": 360,
                                                    "check_env": 0,
                                                    "clear_provided_target": 0,
                                                    "height": 2,
                                                    "lower_bound": 0,
                                                    "max range": 10,
                                                    "max targets": 1,
                                                    "method": 1,
                                                    "min range": 0,
                                                    "miss action": 8458,
                                                    "target_enemy": 1,
                                                    "target_friend": 0,
                                                    "target_self": 0,
                                                    "upper_bound": 5,
                                                    "use_attack_priority": 1,
                                                    "use_picked_target": 1
                                                },
                                                "kids": {
                                                    "8458": {
                                                        "name": {
                                                            "templateID": 3,
                                                            "behaviorTemplateName": "And",
                                                            "effectID": 0
                                                        },
                                                        "hasKids": true,
                                                        "info": {
                                                            "behavior 1": 8456,
                                                            "behavior 2": 8448
                                                        },
                                                        "kids": {}
                                                    }
                                                }
                                            }
                                        }
                                    }
                                }
                            },
                            "8459": {
                                "name": {
                                    "templateID": 3,
                                    "behaviorTemplateName": "And",
                                    "effectID": 0
                                },
                                "hasKids": true,
                                "info": {
                                    "behavior 1": 8460,
                                    "behavior 2": 8462,
                                    "behavior 3": 8463,
                                    "behavior 4": 8464
                                },
                                "kids": {
                                    "8464": {
                                        "name": {
                                            "templateID": 2,
                                            "behaviorTemplateName": "TacArc",
                                            "effectID": 0
                                        },
                                        "hasKids": true,
                                        "info": {
                                            "action": 8465,
                                            "angle": 90,
                                            "check_env": 0,
                                            "clear_provided_target": 0,
                                            "height": 2,
                                            "lower_bound": 0,
                                            "max range": 10,
                                            "max targets": 1,
                                            "method": 1,
                                            "min range": 0,
                                            "miss action": 8474,
                                            "target_enemy": 1,
                                            "target_friend": 0,
                                            "target_self": 0,
                                            "upper_bound": 5,
                                            "use_attack_priority": 1,
                                            "use_picked_target": 1
                                        },
                                        "kids": {
                                            "8465": {
                                                "name": {
                                                    "templateID": 3,
                                                    "behaviorTemplateName": "And",
                                                    "effectID": 0
                                                },
                                                "hasKids": true,
                                                "info": {
                                                    "behavior 1": 8466,
                                                    "behavior 2": 8455,
                                                    "behavior 3": 8473
                                                },
                                                "kids": {
                                                    "8466": {
                                                        "name": {
                                                            "templateID": 18,
                                                            "behaviorTemplateName": "AttackDelay",
                                                            "effectID": 1941
                                                        },
                                                        "hasKids": true,
                                                        "info": {
                                                            "action": 8467,
                                                            "delay": 0
                                                        },
                                                        "kids": {
                                                            "8467": {
                                                                "name": {
                                                                    "templateID": 2,
                                                                    "behaviorTemplateName": "TacArc",
                                                                    "effectID": 1942
                                                                },
                                                                "hasKids": true,
                                                                "info": {
                                                                    "action": 8468,
                                                                    "angle": 90,
                                                                    "angle_weight": 0,
                                                                    "blocked action": 8358,
                                                                    "check_env": 1,
                                                                    "clear_provided_target": 0,
                                                                    "distance_weight": 0,
                                                                    "height": 2,
                                                                    "lower_bound": 0,
                                                                    "max range": 9,
                                                                    "max targets": 1,
                                                                    "method": 1,
                                                                    "min range": 0,
                                                                    "target_enemy": 1,
                                                                    "target_friend": 0,
                                                                    "target_self": 0,
                                                                    "upper_bound": 5,
                                                                    "use_attack_priority": 1,
                                                                    "use_picked_target": 0
                                                                },
                                                                "kids": {
                                                                    "8468": {
                                                                        "name": {
                                                                            "templateID": 1,
                                                                            "behaviorTemplateName": "BasicAttack",
                                                                            "effectID": 1943
                                                                        },
                                                                        "hasKids": true,
                                                                        "info": {
                                                                            "dir_angle_xz": -25,
                                                                            "dir_angle_y": 0,
                                                                            "dir_force": 12,
                                                                            "max damage": 2,
                                                                            "min damage": 2,
                                                                            "on_success": 8469
                                                                        },
                                                                        "kids": {
                                                                            "8469": {
                                                                                "name": {
                                                                                    "templateID": 3,
                                                                                    "behaviorTemplateName": "And",
                                                                                    "effectID": 0
                                                                                },
                                                                                "hasKids": true,
                                                                                "info": {
                                                                                    "behavior 1": 8470,
                                                                                    "behavior 2": 8472,
                                                                                    "behavior 3": 8357
                                                                                },
                                                                                "kids": {
                                                                                    "8470": {
                                                                                        "name": {
                                                                                            "templateID": 16,
                                                                                            "behaviorTemplateName": "Duration",
                                                                                            "effectID": 0
                                                                                        },
                                                                                        "hasKids": true,
                                                                                        "info": {
                                                                                            "action": 8471,
                                                                                            "duration": 0
                                                                                        },
                                                                                        "kids": {
                                                                                            "8471": {
                                                                                                "name": {
                                                                                                    "templateID": 15,
                                                                                                    "behaviorTemplateName": "Stun",
                                                                                                    "effectID": 0
                                                                                                },
                                                                                                "hasKids": true,
                                                                                                "info": {
                                                                                                    "cant_attack": 1,
                                                                                                    "cant_equip": 0,
                                                                                                    "cant_interact": 0,
                                                                                                    "cant_move": 1,
                                                                                                    "cant_turn": 1
                                                                                                },
                                                                                                "kids": {}
                                                                                            }
                                                                                        }
                                                                                    },
                                                                                    "8472": {
                                                                                        "name": {
                                                                                            "templateID": 17,
                                                                                            "behaviorTemplateName": "Knockback",
                                                                                            "effectID": 0
                                                                                        },
                                                                                        "hasKids": true,
                                                                                        "info": {
                                                                                            "angle": 10,
                                                                                            "strength": 2
                                                                                        },
                                                                                        "kids": {}
                                                                                    }
                                                                                }
                                                                            }
                                                                        }
                                                                    }
                                                                }
                                                            }
                                                        }
                                                    },
                                                    "8473": {
                                                        "name": {
                                                            "templateID": 40,
                                                            "behaviorTemplateName": "ForceMovement",
                                                            "effectID": 0
                                                        },
                                                        "hasKids": true,
                                                        "info": {
                                                            "duration": 0,
                                                            "forward": 0,
                                                            "left": 0,
                                                            "move_target": 0,
                                                            "relative": 1,
                                                            "yaw": 0,
                                                            "yaw_abs": 0
                                                        },
                                                        "kids": {}
                                                    }
                                                }
                                            },
                                            "8474": {
                                                "name": {
                                                    "templateID": 2,
                                                    "behaviorTemplateName": "TacArc",
                                                    "effectID": 0
                                                },
                                                "hasKids": true,
                                                "info": {
                                                    "action": 8465,
                                                    "angle": 360,
                                                    "check_env": 0,
                                                    "clear_provided_target": 0,
                                                    "height": 2,
                                                    "lower_bound": 0,
                                                    "max range": 10,
                                                    "max targets": 1,
                                                    "method": 1,
                                                    "min range": 0,
                                                    "miss action": 8475,
                                                    "target_enemy": 1,
                                                    "target_friend": 0,
                                                    "target_self": 0,
                                                    "upper_bound": 5,
                                                    "use_attack_priority": 1,
                                                    "use_picked_target": 1
                                                },
                                                "kids": {
                                                    "8475": {
                                                        "name": {
                                                            "templateID": 3,
                                                            "behaviorTemplateName": "And",
                                                            "effectID": 0
                                                        },
                                                        "hasKids": true,
                                                        "info": {
                                                            "behavior 1": 8473,
                                                            "behavior 2": 8466
                                                        },
                                                        "kids": {}
                                                    }
                                                }
                                            }
                                        }
                                    }
                                }
                            },
                            "8476": {
                                "name": {
                                    "templateID": 3,
                                    "behaviorTemplateName": "And",
                                    "effectID": 0
                                },
                                "hasKids": true,
                                "info": {
                                    "behavior 1": 8477,
                                    "behavior 2": 8479,
                                    "behavior 3": 8480,
                                    "behavior 4": 8481
                                },
                                "kids": {
                                    "8477": {
                                        "name": {
                                            "templateID": 16,
                                            "behaviorTemplateName": "Duration",
                                            "effectID": 0
                                        },
                                        "hasKids": true,
                                        "info": {
                                            "action": 8478,
                                            "duration": 0
                                        },
                                        "kids": {
                                            "8478": {
                                                "name": {
                                                    "templateID": 15,
                                                    "behaviorTemplateName": "Stun",
                                                    "effectID": 0
                                                },
                                                "hasKids": true,
                                                "info": {
                                                    "cant_attack": 0,
                                                    "cant_equip": 1,
                                                    "cant_interact": 1,
                                                    "cant_move": 1,
                                                    "cant_turn": 1,
                                                    "stun_caster": 1
                                                },
                                                "kids": {}
                                            }
                                        }
                                    },
                                    "8479": {
                                        "name": {
                                            "templateID": 42,
                                            "behaviorTemplateName": "AlterCooldown",
                                            "effectID": 0
                                        },
                                        "hasKids": true,
                                        "info": {
                                            "add": 0,
                                            "amount": 1
                                        },
                                        "kids": {}
                                    },
                                    "8480": {
                                        "name": {
                                            "templateID": 47,
                                            "behaviorTemplateName": "AlterChainDelay",
                                            "effectID": 0
                                        },
                                        "hasKids": true,
                                        "info": {
                                            "chain_action": 8440,
                                            "new_delay": 1
                                        },
                                        "kids": {}
                                    },
                                    "8481": {
                                        "name": {
                                            "templateID": 2,
                                            "behaviorTemplateName": "TacArc",
                                            "effectID": 0
                                        },
                                        "hasKids": true,
                                        "info": {
                                            "action": 8482,
                                            "angle": 90,
                                            "check_env": 0,
                                            "clear_provided_target": 0,
                                            "height": 2,
                                            "lower_bound": 0,
                                            "max range": 10,
                                            "max targets": 1,
                                            "method": 1,
                                            "min range": 0,
                                            "miss action": 8491,
                                            "target_enemy": 1,
                                            "target_friend": 0,
                                            "target_self": 0,
                                            "upper_bound": 5,
                                            "use_attack_priority": 1,
                                            "use_picked_target": 1
                                        },
                                        "kids": {
                                            "8482": {
                                                "name": {
                                                    "templateID": 3,
                                                    "behaviorTemplateName": "And",
                                                    "effectID": 0
                                                },
                                                "hasKids": true,
                                                "info": {
                                                    "behavior 1": 8483,
                                                    "behavior 2": 8455,
                                                    "behavior 3": 8490
                                                },
                                                "kids": {
                                                    "8483": {
                                                        "name": {
                                                            "templateID": 18,
                                                            "behaviorTemplateName": "AttackDelay",
                                                            "effectID": 1944
                                                        },
                                                        "hasKids": true,
                                                        "info": {
                                                            "action": 8484,
                                                            "delay": 0
                                                        },
                                                        "kids": {
                                                            "8484": {
                                                                "name": {
                                                                    "templateID": 2,
                                                                    "behaviorTemplateName": "TacArc",
                                                                    "effectID": 1945
                                                                },
                                                                "hasKids": true,
                                                                "info": {
                                                                    "action": 8485,
                                                                    "angle": 90,
                                                                    "angle_weight": 0,
                                                                    "blocked action": 8358,
                                                                    "check_env": 1,
                                                                    "clear_provided_target": 0,
                                                                    "distance_weight": 0,
                                                                    "height": 2,
                                                                    "lower_bound": 0,
                                                                    "max range": 9,
                                                                    "max targets": 1,
                                                                    "method": 1,
                                                                    "min range": 0,
                                                                    "target_enemy": 1,
                                                                    "target_friend": 0,
                                                                    "target_self": 0,
                                                                    "upper_bound": 5,
                                                                    "use_attack_priority": 1,
                                                                    "use_picked_target": 0
                                                                },
                                                                "kids": {
                                                                    "8485": {
                                                                        "name": {
                                                                            "templateID": 1,
                                                                            "behaviorTemplateName": "BasicAttack",
                                                                            "effectID": 1946
                                                                        },
                                                                        "hasKids": true,
                                                                        "info": {
                                                                            "dir_angle_xz": -25,
                                                                            "dir_angle_y": 0,
                                                                            "dir_force": 12,
                                                                            "max damage": 2,
                                                                            "min damage": 2,
                                                                            "on_success": 8486
                                                                        },
                                                                        "kids": {
                                                                            "8486": {
                                                                                "name": {
                                                                                    "templateID": 3,
                                                                                    "behaviorTemplateName": "And",
                                                                                    "effectID": 0
                                                                                },
                                                                                "hasKids": true,
                                                                                "info": {
                                                                                    "behavior 1": 8487,
                                                                                    "behavior 2": 8489,
                                                                                    "behavior 3": 8357
                                                                                },
                                                                                "kids": {
                                                                                    "8487": {
                                                                                        "name": {
                                                                                            "templateID": 16,
                                                                                            "behaviorTemplateName": "Duration",
                                                                                            "effectID": 0
                                                                                        },
                                                                                        "hasKids": true,
                                                                                        "info": {
                                                                                            "action": 8488,
                                                                                            "duration": 0
                                                                                        },
                                                                                        "kids": {
                                                                                            "8488": {
                                                                                                "name": {
                                                                                                    "templateID": 15,
                                                                                                    "behaviorTemplateName": "Stun",
                                                                                                    "effectID": 0
                                                                                                },
                                                                                                "hasKids": true,
                                                                                                "info": {
                                                                                                    "cant_attack": 1,
                                                                                                    "cant_equip": 0,
                                                                                                    "cant_interact": 0,
                                                                                                    "cant_move": 1,
                                                                                                    "cant_turn": 1
                                                                                                },
                                                                                                "kids": {}
                                                                                            }
                                                                                        }
                                                                                    },
                                                                                    "8489": {
                                                                                        "name": {
                                                                                            "templateID": 17,
                                                                                            "behaviorTemplateName": "Knockback",
                                                                                            "effectID": 0
                                                                                        },
                                                                                        "hasKids": true,
                                                                                        "info": {
                                                                                            "angle": 10,
                                                                                            "strength": 2
                                                                                        },
                                                                                        "kids": {}
                                                                                    }
                                                                                }
                                                                            }
                                                                        }
                                                                    }
                                                                }
                                                            }
                                                        }
                                                    },
                                                    "8490": {
                                                        "name": {
                                                            "templateID": 40,
                                                            "behaviorTemplateName": "ForceMovement",
                                                            "effectID": 0
                                                        },
                                                        "hasKids": true,
                                                        "info": {
                                                            "duration": 0,
                                                            "forward": 0,
                                                            "left": 0,
                                                            "move_target": 0,
                                                            "relative": 1,
                                                            "yaw": 0,
                                                            "yaw_abs": 0
                                                        },
                                                        "kids": {}
                                                    }
                                                }
                                            },
                                            "8491": {
                                                "name": {
                                                    "templateID": 2,
                                                    "behaviorTemplateName": "TacArc",
                                                    "effectID": 0
                                                },
                                                "hasKids": true,
                                                "info": {
                                                    "action": 8482,
                                                    "angle": 360,
                                                    "check_env": 0,
                                                    "clear_provided_target": 0,
                                                    "height": 2,
                                                    "lower_bound": 0,
                                                    "max range": 10,
                                                    "max targets": 1,
                                                    "method": 1,
                                                    "min range": 0,
                                                    "miss action": 8492,
                                                    "target_enemy": 1,
                                                    "target_friend": 0,
                                                    "target_self": 0,
                                                    "upper_bound": 5,
                                                    "use_attack_priority": 1,
                                                    "use_picked_target": 1
                                                },
                                                "kids": {
                                                    "8492": {
                                                        "name": {
                                                            "templateID": 3,
                                                            "behaviorTemplateName": "And",
                                                            "effectID": 0
                                                        },
                                                        "hasKids": true,
                                                        "info": {
                                                            "behavior 1": 8490,
                                                            "behavior 2": 8483
                                                        },
                                                        "kids": {}
                                                    }
                                                }
                                            }
                                        }
                                    }
                                }
                            }
                        }
                    }
                }
            }
        }
    }
}