{
    "overview": {
        "hasChargeUp": false,
        "spawnsObject": false,
        "spawnsQuickbuild": false,
        "meleeAttack": false,
        "projectileAttack": false,
        "damageComboArray": [],
        "chargeUpArmorRestore": [],
        "chargeUpImaginationRestore": [],
        "projectileLOTs": [],
        "projectileInfo": {},
        "projectileDamageComboArray": [],
        "chargeUpCombo": 0
    },
    "projectileBehaviorIDs": [],
    "projectileChargeUpBehaviorIDs": [],
    "double_jump_action": {
        "initial_value": 30624
    },
    "falling_action": {
        "initial_value": 30624
    },
    "ground_action": {
        "initial_value": 30630
    },
    "jetpack_action": {
        "initial_value": 0
    },
    "jump_action": {
        "initial_value": 30625
    },
    "30623": {
        "name": {
            "templateID": 6,
            "behaviorTemplateName": "Movement Switch",
            "effectID": 0
        },
        "hasKids": true,
        "info": {
            "double_jump_action": 30624,
            "falling_action": 30624,
            "ground_action": 30630,
            "jetpack_action": 0,
            "jump_action": 30625
        },
        "kids": {
            "30624": {
                "name": {
                    "templateID": 16,
                    "behaviorTemplateName": "Duration",
                    "effectID": 0
                },
                "hasKids": false,
                "info": {},
                "kids": {}
            },
            "30630": {
                "name": {
                    "templateID": 3,
                    "behaviorTemplateName": "And",
                    "effectID": 6731
                },
                "hasKids": true,
                "info": {
                    "behavior 1": 30626,
                    "behavior 2": 30631,
                    "behavior 3": 30628,
                    "behavior 4": 30627
                },
                "kids": {
                    "30626": {
                        "name": {
                            "templateID": 23,
                            "behaviorTemplateName": "Speed",
                            "effectID": 0
                        },
                        "hasKids": true,
                        "info": {
                            "affects_caster": 1,
                            "attack_speed": 0,
                            "run_speed": 510
                        },
                        "kids": {}
                    },
                    "30631": {
                        "name": {
                            "templateID": 8,
                            "behaviorTemplateName": "PlayEffect",
                            "effectID": 6732
                        },
                        "hasKids": false,
                        "info": {},
                        "kids": {}
                    },
                    "30628": {
                        "name": {
                            "templateID": 8,
                            "behaviorTemplateName": "PlayEffect",
                            "effectID": 6730
                        },
                        "hasKids": false,
                        "info": {},
                        "kids": {}
                    },
                    "30627": {
                        "name": {
                            "templateID": 8,
                            "behaviorTemplateName": "PlayEffect",
                            "effectID": 6729
                        },
                        "hasKids": false,
                        "info": {},
                        "kids": {}
                    }
                }
            },
            "0": {
                "hasKids": false,
                "info": {},
                "kids": {}
            },
            "30625": {
                "name": {
                    "templateID": 3,
                    "behaviorTemplateName": "And",
                    "effectID": 0
                },
                "hasKids": true,
                "info": {
                    "behavior 1": 30626,
                    "behavior 2": 30627,
                    "behavior 3": 30628
                },
                "kids": {}
            }
        }
    }
}